pymlconf/__init__.py
pymlconf/errors.py
pymlconf/models.py
pymlconf/yamlhelper.py
tests/__init__.py
tests/test_binary.py
tests/test_delattribute.py
tests/test_diferred_root.py
tests/test_merge.py
tests/test_root.py
tests/test_yaml_syntax.py
pymlconf-2.5.9.dist-info/LICENSE
pymlconf-2.5.9.dist-info/METADATA
pymlconf-2.5.9.dist-info/WHEEL
pymlconf-2.5.9.dist-info/top_level.txt
pymlconf-2.5.9.dist-info/RECORD
