Metadata-Version: 2.1
Name: pymlconf
Version: 2.5.9
Summary: Another configuration library using yaml
Home-page: http://github.com/pylover/pymlconf
Author: Vahid Mardani
Author-email: vahid.mardani@gmail.com
License: UNKNOWN
Platform: any
Classifier: Development Status :: 5 - Production/Stable
Classifier: License :: OSI Approved :: MIT License
Classifier: Intended Audience :: Developers
Classifier: Operating System :: OS Independent
Classifier: Programming Language :: Python :: 3.6
Classifier: Topic :: Software Development :: Libraries
Requires-Dist: pyyaml (>=5.3)
